{
  "출처": "Brand Archive",
  "브랜드명": "Siuru – Tartu Cultural Centre",
  "슬러그": "siuru-–-tartu-cultural-centre",
  "원본URL": "https://brandarchive.xyz/identity/siuru-–-tartu-cultural-centre",
  "연도": 2025,
  "디자이너": [
    "Bond"
  ],
  "소속컬렉션": {
    "이름": "Museums, Galleries & Libraries",
    "슬러그": "museum-brands"
  },
  "PRO잠금여부": true,
  "히스토리": "공개 상세 페이지에서 별도 서술형 히스토리 텍스트는 제공되지 않음",
  "상세정보": {
    "브랜드명": "500",
    "디자이너": null,
    "연도": null,
    "태그": null,
    "섹션": [],
    "컬러": [],
    "서체정보": null,
    "히스토리": "공개 상세 페이지에서 별도 서술형 히스토리 텍스트는 제공되지 않음"
  },
  "다운로드설정": "이미지만 저장",
  "에셋요약": {
    "전체에셋수": 25,
    "이미지수": 22,
    "영상수": 3,
    "이번에저장한파일수": 22
  },
  "에셋": [
    {
      "종류": "이미지",
      "원본파일명": "siuru-5.jpg",
      "MIME": "image/jpeg",
      "너비": 1921,
      "높이": 1081,
      "원본URL": "https://cdn.sanity.io/images/rn4tswnp/production/2690c601f6581424fdba01f6f86996010af757c8-1921x1081.jpg",
      "로컬경로": "archive\\brandarchive\\identities\\siuru-–-tartu-cultural-centre\\assets\\001-siuru-5.jpg"
    },
    {
      "종류": "이미지",
      "원본파일명": "file-7 copya.jpg",
      "MIME": "image/jpeg",
      "너비": 1920,
      "높이": 1080,
      "원본URL": "https://cdn.sanity.io/images/rn4tswnp/production/96ab454338da93b44b25b60abce12648dabec97f-1920x1080.jpg",
      "로컬경로": "archive\\brandarchive\\identities\\siuru-–-tartu-cultural-centre\\assets\\002-file-7-copya.jpg"
    },
    {
      "종류": "이미지",
      "원본파일명": "file-7 copybb.jpg",
      "MIME": "image/jpeg",
      "너비": 1920,
      "높이": 1080,
      "원본URL": "https://cdn.sanity.io/images/rn4tswnp/production/05f7625a7bf55bb3aabcbefa687cf92793b9df83-1920x1080.jpg",
      "로컬경로": "archive\\brandarchive\\identities\\siuru-–-tartu-cultural-centre\\assets\\003-file-7-copybb.jpg"
    },
    {
      "종류": "이미지",
      "원본파일명": "67f7ab21e329228ca064bb39_06.2_siuru-pieces.jpg",
      "MIME": "image/jpeg",
      "너비": 2257,
      "높이": 2257,
      "원본URL": "https://cdn.sanity.io/images/rn4tswnp/production/672c3490d76070d9e0580826667fa29fb1ab12f1-2257x2257.jpg",
      "로컬경로": "archive\\brandarchive\\identities\\siuru-–-tartu-cultural-centre\\assets\\004-67f7ab21e329228ca064bb39_06.2_siuru-pieces.jpg"
    },
    {
      "종류": "이미지",
      "원본파일명": "67f7ab21e329228ca064bb39_06.2_siuru.jpg",
      "MIME": "image/jpeg",
      "너비": 2600,
      "높이": 2600,
      "원본URL": "https://cdn.sanity.io/images/rn4tswnp/production/3ad05640199f7630740c78540f18a51264907aed-2600x2600.jpg",
      "로컬경로": "archive\\brandarchive\\identities\\siuru-–-tartu-cultural-centre\\assets\\005-67f7ab21e329228ca064bb39_06.2_siuru.jpg"
    },
    {
      "종류": "이미지",
      "원본파일명": "67f7ab2070939ac5b4232300_03_siuru-posters.jpg",
      "MIME": "image/jpeg",
      "너비": 3841,
      "높이": 2164,
      "원본URL": "https://cdn.sanity.io/images/rn4tswnp/production/2e148be2a337111602a3f93822b24a4fb068777a-3841x2164.jpg",
      "로컬경로": "archive\\brandarchive\\identities\\siuru-–-tartu-cultural-centre\\assets\\006-67f7ab2070939ac5b4232300_03_siuru-posters.jpg"
    },
    {
      "종류": "이미지",
      "원본파일명": "Siuru-3.jpg",
      "MIME": "image/jpeg",
      "너비": 1921,
      "높이": 1081,
      "원본URL": "https://cdn.sanity.io/images/rn4tswnp/production/a28477653ab59128be8c0a651fba33f17b154e8f-1921x1081.jpg",
      "로컬경로": "archive\\brandarchive\\identities\\siuru-–-tartu-cultural-centre\\assets\\007-Siuru-3.jpg"
    },
    {
      "종류": "이미지",
      "원본파일명": "Siuru-4-1.jpg",
      "MIME": "image/jpeg",
      "너비": 1921,
      "높이": 1081,
      "원본URL": "https://cdn.sanity.io/images/rn4tswnp/production/fae3eda20545a6c146a46573c103705c076e06ad-1921x1081.jpg",
      "로컬경로": "archive\\brandarchive\\identities\\siuru-–-tartu-cultural-centre\\assets\\008-Siuru-4-1.jpg"
    },
    {
      "종류": "이미지",
      "원본파일명": "67f7ab1e9192c6899707baad_09.1_siuru_wine.jpg",
      "MIME": "image/jpeg",
      "너비": 1506,
      "높이": 1882,
      "원본URL": "https://cdn.sanity.io/images/rn4tswnp/production/30af01b77930a0f7f7693e25d75adf6548030b64-1506x1882.jpg",
      "로컬경로": "archive\\brandarchive\\identities\\siuru-–-tartu-cultural-centre\\assets\\009-67f7ab1e9192c6899707baad_09.1_siuru_wine.jpg"
    },
    {
      "종류": "이미지",
      "원본파일명": "67f7ab1f2c59b6fc5642bb75_07_siuru-icon.jpg",
      "MIME": "image/jpeg",
      "너비": 1830,
      "높이": 869,
      "원본URL": "https://cdn.sanity.io/images/rn4tswnp/production/2df1facc11aa7f593be9da7a12bd062b11869c0d-1830x869.jpg",
      "로컬경로": "archive\\brandarchive\\identities\\siuru-–-tartu-cultural-centre\\assets\\010-67f7ab1f2c59b6fc5642bb75_07_siuru-icon.jpg"
    },
    {
      "종류": "이미지",
      "원본파일명": "67f7ab1ff43e4ff862ad0e09_05.2_siuru-card.jpg",
      "MIME": "image/jpeg",
      "너비": 1506,
      "높이": 1882,
      "원본URL": "https://cdn.sanity.io/images/rn4tswnp/production/5235aa37c0d5a061653dbbb43d4ea4e0797a7f97-1506x1882.jpg",
      "로컬경로": "archive\\brandarchive\\identities\\siuru-–-tartu-cultural-centre\\assets\\011-67f7ab1ff43e4ff862ad0e09_05.2_siuru-card.jpg"
    },
    {
      "종류": "이미지",
      "원본파일명": "67f7ab1fd0cb080fa6b3581f_08_siuru_booklet.jpg",
      "MIME": "image/jpeg",
      "너비": 3060,
      "높이": 1724,
      "원본URL": "https://cdn.sanity.io/images/rn4tswnp/production/586d2aa136ac72cb0d8445c717d6dcb69ad7feef-3060x1724.jpg",
      "로컬경로": "archive\\brandarchive\\identities\\siuru-–-tartu-cultural-centre\\assets\\012-67f7ab1fd0cb080fa6b3581f_08_siuru_booklet.jpg"
    },
    {
      "종류": "이미지",
      "원본파일명": "67f7ab1fc397656e8c336a87_09.2_siuru-shirt.jpg",
      "MIME": "image/jpeg",
      "너비": 3305,
      "높이": 4131,
      "원본URL": "https://cdn.sanity.io/images/rn4tswnp/production/7fa2eecd57122662d05ccb888d908c82fad361dd-3305x4131.jpg",
      "로컬경로": "archive\\brandarchive\\identities\\siuru-–-tartu-cultural-centre\\assets\\013-67f7ab1fc397656e8c336a87_09.2_siuru-shirt.jpg"
    },
    {
      "종류": "이미지",
      "원본파일명": "Siuru-7.jpg",
      "MIME": "image/jpeg",
      "너비": 984,
      "높이": 1077,
      "원본URL": "https://cdn.sanity.io/images/rn4tswnp/production/5debc37305cb65b6b07306c6ad049cbd1bfdab0e-984x1077.jpg",
      "로컬경로": "archive\\brandarchive\\identities\\siuru-–-tartu-cultural-centre\\assets\\014-Siuru-7.jpg"
    },
    {
      "종류": "이미지",
      "원본파일명": "static-img.aripaev.ee.jpeg",
      "MIME": "image/jpeg",
      "너비": 1484,
      "높이": 757,
      "원본URL": "https://cdn.sanity.io/images/rn4tswnp/production/cc047d2cb37cae95649f0565e929654103c91461-1484x757.jpg",
      "로컬경로": "archive\\brandarchive\\identities\\siuru-–-tartu-cultural-centre\\assets\\015-static-img.aripaev.ee.jpeg"
    },
    {
      "종류": "이미지",
      "원본파일명": "67f7ab1f2c59b6fc5642bb75_07_siuru-icon c.jpg",
      "MIME": "image/jpeg",
      "너비": 1226,
      "높이": 870,
      "원본URL": "https://cdn.sanity.io/images/rn4tswnp/production/7097b17bf02fb996f3a73318ce2de6a47a8d6ccc-1226x870.jpg",
      "로컬경로": "archive\\brandarchive\\identities\\siuru-–-tartu-cultural-centre\\assets\\016-67f7ab1f2c59b6fc5642bb75_07_siuru-icon-c.jpg"
    },
    {
      "종류": "이미지",
      "원본파일명": "468547122_1167813034858360_7965389801908478085_n.jpg",
      "MIME": "image/jpeg",
      "너비": 1031,
      "높이": 540,
      "원본URL": "https://cdn.sanity.io/images/rn4tswnp/production/aff447a300d9cdd3a164212fd916afef7cc0d9fb-1031x540.jpg",
      "로컬경로": "archive\\brandarchive\\identities\\siuru-–-tartu-cultural-centre\\assets\\017-468547122_1167813034858360_7965389801908478085_n.jpg"
    },
    {
      "종류": "이미지",
      "원본파일명": "483835632_1251004286539234_7719481488449560142_n.jpg",
      "MIME": "image/jpeg",
      "너비": 1921,
      "높이": 1006,
      "원본URL": "https://cdn.sanity.io/images/rn4tswnp/production/cffaf5c3699c1dc8a801d0031cba5515d0e1a505-1921x1006.jpg",
      "로컬경로": "archive\\brandarchive\\identities\\siuru-–-tartu-cultural-centre\\assets\\018-483835632_1251004286539234_7719481488449560142_n.jpg"
    },
    {
      "종류": "이미지",
      "원본파일명": "A.jpg",
      "MIME": "image/jpeg",
      "너비": 2560,
      "높이": 1440,
      "원본URL": "https://cdn.sanity.io/images/rn4tswnp/production/ebe363450c7a5c8b754fd245276bd9862bd0425e-2560x1440.jpg",
      "로컬경로": "archive\\brandarchive\\identities\\siuru-–-tartu-cultural-centre\\assets\\019-A.jpg"
    },
    {
      "종류": "이미지",
      "원본파일명": "B.jpg",
      "MIME": "image/jpeg",
      "너비": 2560,
      "높이": 1440,
      "원본URL": "https://cdn.sanity.io/images/rn4tswnp/production/24f77402fd490e7cc8d31ccdfe2920604fba783b-2560x1440.jpg",
      "로컬경로": "archive\\brandarchive\\identities\\siuru-–-tartu-cultural-centre\\assets\\020-B.jpg"
    },
    {
      "종류": "이미지",
      "원본파일명": "02_siuru-ree_loop copy.jpg",
      "MIME": "image/jpeg",
      "너비": 2560,
      "높이": 1440,
      "원본URL": "https://cdn.sanity.io/images/rn4tswnp/production/6852b133c47d186d7cef19010eb351bc4bf41f9a-2560x1440.jpg",
      "로컬경로": "archive\\brandarchive\\identities\\siuru-–-tartu-cultural-centre\\assets\\021-02_siuru-ree_loop-copy.jpg"
    },
    {
      "종류": "이미지",
      "원본파일명": "2_siuru-reel_loop copy.jpg",
      "MIME": "image/jpeg",
      "너비": 2560,
      "높이": 1440,
      "원본URL": "https://cdn.sanity.io/images/rn4tswnp/production/a6b585a0d912e4160331600af605087c5fbb1fee-2560x1440.jpg",
      "로컬경로": "archive\\brandarchive\\identities\\siuru-–-tartu-cultural-centre\\assets\\022-2_siuru-reel_loop-copy.jpg"
    }
  ]
}